mininterface/__init__.py
mininterface/__main__.py
mininterface/_lib/__init__.py
mininterface/_lib/argparse_support.py
mininterface/_lib/auxiliary.py
mininterface/_lib/cli_flags.py
mininterface/_lib/cli_parser.py
mininterface/_lib/cli_utils.py
mininterface/_lib/config_file.py
mininterface/_lib/dataclass_creation.py
mininterface/_lib/form_dict.py
mininterface/_lib/future_compatibility.py
mininterface/_lib/redirectable.py
mininterface/_lib/run.py
mininterface/_lib/shortcuts.py
mininterface/_lib/showcase.py
mininterface/_lib/start.py
mininterface/_lib/tyro_patches.py
mininterface/_mininterface/__init__.py
mininterface/_mininterface/adaptor.py
mininterface/_mininterface/mixin.py
mininterface/_text_interface/__init__.py
mininterface/_text_interface/adaptor.py
mininterface/_text_interface/facet.py
mininterface/_text_interface/timeout.py
mininterface/_textual_interface/__init__.py
mininterface/_textual_interface/adaptor.py
mininterface/_textual_interface/button_contents.py
mininterface/_textual_interface/facet.py
mininterface/_textual_interface/file_picker_input.py
mininterface/_textual_interface/form_contents.py
mininterface/_textual_interface/secret_input.py
mininterface/_textual_interface/style.tcss
mininterface/_textual_interface/textual_app.py
mininterface/_textual_interface/timeout.py
mininterface/_textual_interface/widgets.py
mininterface/_tk_interface/__init__.py
mininterface/_tk_interface/adaptor.py
mininterface/_tk_interface/date_entry.py
mininterface/_tk_interface/external_fix.py
mininterface/_tk_interface/facet.py
mininterface/_tk_interface/redirect_text_tkinter.py
mininterface/_tk_interface/secret_entry.py
mininterface/_tk_interface/select_input.py
mininterface/_tk_interface/timeout.py
mininterface/_tk_interface/utils.py
mininterface/_web_interface/__init__.py
mininterface/_web_interface/app.py
mininterface/_web_interface/child_adaptor.py
mininterface/_web_interface/parent_adaptor.py
mininterface/cli.py
mininterface/exceptions.py
mininterface/experimental.py
mininterface-1.2.1.dist-info/METADATA
mininterface-1.2.1.dist-info/WHEEL
mininterface-1.2.1.dist-info/entry_points.txt
mininterface-1.2.1.dist-info/licenses/LICENSE
mininterface-1.2.1.dist-info/RECORD
