Metadata-Version: 2.4
Name: mininterface
Version: 1.2.1
Summary: CLI & dialog toolkit – a minimal interface to Python application (GUI, TUI, CLI + config files, web)
License: LGPL-3.0-or-later
License-File: LICENSE
Author: Edvard Rejthar
Author-email: edvard.rejthar@nic.cz
Requires-Python: >=3.10,<4.0
Classifier: License :: OSI Approved :: GNU Lesser General Public License v3 or later (LGPLv3+)
Classifier: Programming Language :: Python :: 3
Classifier: Programming Language :: Python :: 3.10
Classifier: Programming Language :: Python :: 3.11
Classifier: Programming Language :: Python :: 3.12
Classifier: Programming Language :: Python :: 3.13
Classifier: Programming Language :: Python :: 3.14
Provides-Extra: all
Provides-Extra: basic
Provides-Extra: gui
Provides-Extra: img
Provides-Extra: tui
Provides-Extra: ui
Provides-Extra: web
Requires-Dist: annotated-types
Requires-Dist: autocombobox (==1.4.2) ; extra == "gui" or extra == "ui" or extra == "all"
Requires-Dist: humanize ; extra == "basic" or extra == "img" or extra == "tui" or extra == "gui" or extra == "web" or extra == "ui" or extra == "all"
Requires-Dist: pillow ; extra == "img" or extra == "gui" or extra == "ui" or extra == "all"
Requires-Dist: pyyaml ; extra == "basic" or extra == "img" or extra == "tui" or extra == "gui" or extra == "web" or extra == "ui" or extra == "all"
Requires-Dist: simple_term_menu
Requires-Dist: textual (<2.0.0) ; extra == "basic" or extra == "img" or extra == "tui" or extra == "gui" or extra == "web" or extra == "ui" or extra == "all"
Requires-Dist: textual-serve ; extra == "web" or extra == "ui" or extra == "all"
Requires-Dist: textual_imageview ; extra == "img" or extra == "tui" or extra == "ui" or extra == "all"
Requires-Dist: tkcalendar ; extra == "gui" or extra == "ui" or extra == "all"
Requires-Dist: tkinter-tooltip ; extra == "basic" or extra == "img" or extra == "tui" or extra == "gui" or extra == "web" or extra == "ui" or extra == "all"
Requires-Dist: tkinter_form (==0.2.1) ; extra == "basic" or extra == "img" or extra == "tui" or extra == "gui" or extra == "web" or extra == "ui" or extra == "all"
Requires-Dist: tkscrollableframe ; extra == "basic" or extra == "img" or extra == "tui" or extra == "gui" or extra == "web" or extra == "ui" or extra == "all"
Requires-Dist: tyro (>=0.9.31,<0.10.0) ; extra == "basic" or extra == "img" or extra == "tui" or extra == "gui" or extra == "web" or extra == "ui" or extra == "all"
Project-URL: Homepage, https://github.com/CZ-NIC/mininterface
